{
  "sentence": "هؤلاء طلاب مجتهدون",
  "slug": "haulai-tullabun-mujtahidun",
  "lessonName": "الإعراب والبناء",
  "words": [
    {
      "word": "هؤلاء",
      "irab": "اسم إشارة مبني على الكسر في محل رفع مبتدأ."
    },
    {
      "word": "طلاب",
      "irab": "خبر المبتدأ مرفوع وعلامة رفعه الضمة الظاهرة على آخره."
    },
    {
      "word": "مجتهدون",
      "irab": "نعت مرفوع وعلامة رفعه الواو لأنه جمع مذكر سالم."
    }
  ],
  "explanation": "كلمة (هؤلاء) من الأسماء المبنية ولزمت الكسر، بينما (طلاب) و(مجتهدون) أسماء معربة."
}