{
  "lesson_id": "aldamaer",
  "language": "ar",
  "title": "الضمائر",
  "sections": [
    {
      "id": "s001",
      "type": "heading",
      "text": "الضمائر"
    },
    {
      "id": "s002",
      "type": "highlight",
      "label": "تعريف",
      "text": "الضمير اسم جامد مبنيٌّ يدلُّ على متكلمٍ، أو مخاطَبٍ، أو غائبٍ، ويُغني عن ذكر الاسم الظاهر."
    },
    {
      "id": "s003",
      "type": "example",
      "style": "sentences",
      "items": [
        {
          "text": "– أنا أَدْرُسُ بجدٍّ .",
          "underlined": [
            "أنا"
          ]
        },
        {
          "text": "– أنتَ مجتهدٌ .",
          "underlined": [
            "أنتَ"
          ]
        },
        {
          "text": "– هو طالبٌ نشيطٌ .",
          "underlined": [
            "هو"
          ]
        }
      ]
    },
    {
      "id": "s004",
      "type": "heading",
      "text": "أقسام الضمائر"
    },
    {
      "id": "s005",
      "type": "paragraph",
      "text": "تنقسم الضمائر بحسب ظهورها وخفائها إلى قسمين رئيسيين: الضمائر البارزة، والضمائر المستترة."
    },
    {
      "id": "s006",
      "type": "highlight",
      "label": "تعريف",
      "text": "الضمير البارز: هو ما له صورة في اللفظ، أي يُنطق ويُكتب."
    },
    {
      "id": "s007",
      "type": "highlight",
      "label": "تعريف",
      "text": "الضمير المستتر: هو ما ليس له صورة في اللفظ، بل يُقدَّر تقديرًا."
    },
    {
      "id": "s008",
      "type": "heading",
      "text": "أولًا: الضمائر البارزة"
    },
    {
      "id": "s009",
      "type": "paragraph",
      "text": "تنقسم الضمائر البارزة إلى نوعين: ضمائر منفصلة، وضمائر متصلة."
    },
    {
      "id": "s010",
      "type": "heading",
      "text": "1- الضمائر المنفصلة"
    },
    {
      "id": "s011",
      "type": "highlight",
      "label": "تعريف",
      "text": "الضمير المنفصل: هو ما يُنطق به مستقلًّا، ولا يتصل بكلمة أخرى، ويمكن الابتداء به."
    },
    {
      "id": "s012",
      "type": "paragraph",
      "text": "وتنقسم الضمائر المنفصلة بحسب موقعها الإعرابي إلى نوعين: ضمائر رفع منفصلة، وضمائر نصب منفصلة."
    },
    {
      "id": "s013",
      "type": "heading",
      "text": "أ- ضمائر الرفع المنفصلة"
    },
    {
      "id": "s014",
      "type": "table",
      "headers": [
        "الضمير",
        "الدلالة",
        "المثال"
      ],
      "rows": [
        [
          "أنا",
          "للمتكلم المفرد",
          "أنا طالبٌ"
        ],
        [
          "نحنُ",
          "للمتكلم المثنى أو الجمع",
          "نحنُ طلابٌ"
        ],
        [
          "أنتَ",
          "للمخاطب المفرد المذكر",
          "أنتَ مجتهدٌ"
        ],
        [
          "أنتِ",
          "للمخاطبة المفردة المؤنثة",
          "أنتِ مجتهدةٌ"
        ],
        [
          "أنتما",
          "للمخاطب المثنى مذكرًا أو مؤنثًا",
          "أنتما مجتهدانِ"
        ],
        [
          "أنتم",
          "للمخاطب الجمع المذكر",
          "أنتم مجتهدونَ"
        ],
        [
          "أنتنَّ",
          "للمخاطب الجمع المؤنث",
          "أنتنَّ مجتهداتٌ"
        ],
        [
          "هو",
          "للغائب المفرد المذكر",
          "هو طالبٌ"
        ],
        [
          "هي",
          "للغائبة المفردة المؤنثة",
          "هي طالبةٌ"
        ],
        [
          "هما",
          "للغائب المثنى مذكرًا أو مؤنثًا",
          "هما طالبانِ"
        ],
        [
          "هم",
          "للغائب الجمع المذكر",
          "هم طلابٌ"
        ],
        [
          "هنَّ",
          "للغائب الجمع المؤنث",
          "هنَّ طالباتٌ"
        ]
      ]
    },
    {
      "id": "s015",
      "type": "highlight",
      "label": "قاعدة",
      "text": "ضمائر الرفع المنفصلة كلها مبنيةٌ في محلِّ رفعٍ، وتُعرَب بحسب موقعها في الجملة (مبتدأ، أو خبرًا، أو فاعلًا، أو نائبَ فاعلٍ، أو اسمًا لكان وأخواتها)."
    },
    {
      "id": "s016",
      "type": "example",
      "style": "sentences",
      "items": [
        {
          "text": "– أنا مسلمٌ . (مبتدأ)",
          "underlined": [
            "أنا"
          ]
        },
        {
          "text": "– المجتهدُ أنتَ . (خبر)",
          "underlined": [
            "أنتَ"
          ]
        },
        {
          "text": "– ما حضر إلا هو . (فاعل)",
          "underlined": [
            "هو"
          ]
        }
      ]
    },
    {
      "id": "s017",
      "type": "heading",
      "text": "ب- ضمائر النصب المنفصلة"
    },
    {
      "id": "s018",
      "type": "highlight",
      "label": "قاعدة",
      "text": "ضمائر النصب المنفصلة تتكون من (إيَّا) متبوعةً بحرفٍ يدلُّ على المتكلم أو المخاطب أو الغائب."
    },
    {
      "id": "s019",
      "type": "table",
      "headers": [
        "الضمير",
        "الدلالة"
      ],
      "rows": [
        [
          "إيَّايَ",
          "للمتكلم المفرد"
        ],
        [
          "إيَّانا",
          "للمتكلم المثنى أو الجمع"
        ],
        [
          "إيَّاكَ",
          "للمخاطب المفرد المذكر"
        ],
        [
          "إيَّاكِ",
          "للمخاطبة المفردة المؤنثة"
        ],
        [
          "إيَّاكما",
          "للمخاطب المثنى"
        ],
        [
          "إيَّاكم",
          "للمخاطب الجمع المذكر"
        ],
        [
          "إيَّاكنَّ",
          "للمخاطب الجمع المؤنث"
        ],
        [
          "إيَّاهُ",
          "للغائب المفرد المذكر"
        ],
        [
          "إيَّاها",
          "للغائبة المفردة المؤنثة"
        ],
        [
          "إيَّاهما",
          "للغائب المثنى"
        ],
        [
          "إيَّاهم",
          "للغائب الجمع المذكر"
        ],
        [
          "إيَّاهنَّ",
          "للغائب الجمع المؤنث"
        ]
      ]
    },
    {
      "id": "s020",
      "type": "example",
      "style": "sentences",
      "items": [
        {
          "text": "– إيَّاكَ نعبدُ وإيَّاكَ نستعينُ .",
          "underlined": [
            "إيَّاكَ",
            "إيَّاكَ"
          ]
        },
        {
          "text": "– إيَّاهم أكرمتُ .",
          "underlined": [
            "إيَّاهم"
          ]
        },
        {
          "text": "– إيَّاكَ والكذبَ .",
          "underlined": [
            "إيَّاكَ"
          ]
        }
      ]
    },
    {
      "id": "s021",
      "type": "highlight",
      "label": "ملاحظة",
      "text": "ضمائر النصب المنفصلة تُبنى دائمًا في محلِّ نصبٍ، وتقع غالبًا مفعولًا به مقدَّمًا على عامله."
    },
    {
      "id": "s022",
      "type": "heading",
      "text": "2- الضمائر المتصلة"
    },
    {
      "id": "s023",
      "type": "highlight",
      "label": "تعريف",
      "text": "الضمير المتصل: هو ما لا يُنطق به مستقلًّا، بل يتصل بكلمة قبله (فعل، أو اسم، أو حرف)، ولا يمكن الابتداء به."
    },
    {
      "id": "s024",
      "type": "paragraph",
      "text": "وتنقسم الضمائر المتصلة بحسب موقعها الإعرابي إلى ثلاثة أنواع: ضمائر رفع متصلة، وضمائر نصب وجرٍّ مشتركة، وضمير لا يكون إلا في محل جرٍّ."
    },
    {
      "id": "s025",
      "type": "heading",
      "text": "أ- ضمائر الرفع المتصلة"
    },
    {
      "id": "s026",
      "type": "highlight",
      "label": "قاعدة",
      "text": "ضمائر الرفع المتصلة هي: التاء المتحركة (تاء الفاعل)، ونا الفاعلين، وألف الاثنين، وواو الجماعة، وياء المخاطبة، ونون النسوة. وتتصل بالأفعال فقط، وتقع فاعلًا أو نائبَ فاعلٍ أو اسمًا لكان وأخواتها."
    },
    {
      "id": "s027",
      "type": "table",
      "headers": [
        "الضمير",
        "الدلالة",
        "المثال"
      ],
      "rows": [
        [
          "التاء المتحركة",
          "للمتكلم أو المخاطب",
          "كَتَبْتُ، كَتَبْتَ، كَتَبْتِ"
        ],
        [
          "نا الفاعلين",
          "للمتكلم المثنى أو الجمع",
          "كَتَبْنا"
        ],
        [
          "ألف الاثنين",
          "للمثنى الغائب أو المخاطب",
          "كَتَبَا، اكْتُبَا، يَكْتُبَانِ"
        ],
        [
          "واو الجماعة",
          "لجمع المذكر الغائب أو المخاطب",
          "كَتَبُوا، اكْتُبُوا، يَكْتُبُونَ"
        ],
        [
          "ياء المخاطبة",
          "للمخاطبة المؤنثة",
          "اكْتُبِي، تَكْتُبِينَ"
        ],
        [
          "نون النسوة",
          "لجمع الإناث الغائبات أو المخاطبات",
          "كَتَبْنَ، اكْتُبْنَ، يَكْتُبْنَ"
        ]
      ]
    },
    {
      "id": "s028",
      "type": "example",
      "style": "sentences",
      "items": [
        {
          "text": "– كَتَبْتُ الدرسَ .",
          "underlined": [
            "تُ"
          ]
        },
        {
          "text": "– كَتَبْنا الرسالةَ .",
          "underlined": [
            "نا"
          ]
        },
        {
          "text": "– الطالبانِ كَتَبَا الواجبَ .",
          "underlined": [
            "ا"
          ]
        },
        {
          "text": "– الطلابُ كَتَبُوا الدرسَ .",
          "underlined": [
            "وا"
          ]
        },
        {
          "text": "– يا فاطمةُ اكْتُبِي الدرسَ .",
          "underlined": [
            "ي"
          ]
        },
        {
          "text": "– الطالباتُ كَتَبْنَ الدرسَ .",
          "underlined": [
            "نَ"
          ]
        }
      ]
    },
    {
      "id": "s029",
      "type": "heading",
      "text": "ب- الضمائر المتصلة المشتركة (للنصب والجر)"
    },
    {
      "id": "s030",
      "type": "highlight",
      "label": "قاعدة",
      "text": "الضمائر المشتركة هي: ياء المتكلم، وكاف الخطاب، وهاء الغيبة، ونا الفاعلين. وتسمى مشتركة لأنها تكون في محل نصبٍ إذا اتصلت بفعل، وفي محل نصبٍ أو جرٍّ إذا اتصلت باسم، وفي محل جرٍّ إذا اتصلت بحرف جرٍّ."
    },
    {
      "id": "s031",
      "type": "example",
      "style": "sentences",
      "items": [
        {
          "text": "– أكرمَني المعلمُ . (في محل نصب مفعول به)",
          "underlined": [
            "ني"
          ]
        },
        {
          "text": "– كتابي جديدٌ . (في محل جر بالإضافة)",
          "underlined": [
            "ي"
          ]
        },
        {
          "text": "– إنَّني مجتهدٌ . (في محل نصب اسم إنَّ)",
          "underlined": [
            "ني"
          ]
        },
        {
          "text": "– سلَّمَ عليَّ المعلمُ . (في محل جر بحرف الجر)",
          "underlined": [
            "ي"
          ]
        }
      ]
    },
    {
      "id": "s032",
      "type": "table",
      "headers": [
        "الضمير",
        "اتصاله بالفعل",
        "اتصاله بالاسم",
        "اتصاله بالحرف"
      ],
      "rows": [
        [
          "ياء المتكلم",
          "أكرمَني (مفعول به)",
          "كتابي (مضاف إليه)",
          "عليَّ (مجرور)"
        ],
        [
          "كاف الخطاب",
          "أكرمَكَ (مفعول به)",
          "كتابُكَ (مضاف إليه)",
          "عليكَ (مجرور)"
        ],
        [
          "هاء الغيبة",
          "أكرمَهُ (مفعول به)",
          "كتابُهُ (مضاف إليه)",
          "عليهِ (مجرور)"
        ],
        [
          "نا الفاعلين",
          "أكرمَنا (مفعول به)",
          "كتابُنا (مضاف إليه)",
          "علينا (مجرور)"
        ]
      ]
    },
    {
      "id": "s033",
      "type": "highlight",
      "label": "تنبيه",
      "text": "ضمير (نا) يكون في محلِّ رفعٍ إذا كان فاعلًا، كما في (كَتَبْنا)، ويكون في محلِّ نصبٍ أو جرٍّ إذا اتصل باسم أو حرف جرٍّ، كما في (كتابُنا) و(علينا)."
    },
    {
      "id": "s034",
      "type": "heading",
      "text": "ج- الضمير الذي لا يكون إلا في محل جرٍّ"
    },
    {
      "id": "s035",
      "type": "highlight",
      "label": "قاعدة",
      "text": "ضمير المتكلم (ياء النسبة) يتصل بالاسم فيكون في محل جرٍّ بالإضافة، ولا يتصل بالفعل."
    },
    {
      "id": "s036",
      "type": "paragraph",
      "text": "ومن الضمائر التي لا تكون إلا في محل جرٍّ ما يتصل بحروف الجر مباشرة كقولنا: لي، لكَ، لهُ، منهُ، عنهم."
    },
    {
      "id": "s037",
      "type": "example",
      "style": "sentences",
      "items": [
        {
          "text": "– هذا كتابي .",
          "underlined": [
            "ي"
          ]
        },
        {
          "text": "– إنَّ لي صديقًا .",
          "underlined": [
            "ي"
          ]
        },
        {
          "text": "– سلَّمتُ عليه .",
          "underlined": [
            "ه"
          ]
        }
      ]
    },
    {
      "id": "s038",
      "type": "heading",
      "text": "ثانيًا: الضمائر المستترة"
    },
    {
      "id": "s039",
      "type": "highlight",
      "label": "تعريف",
      "text": "الضمير المستتر: هو ضميرٌ لا صورة له في اللفظ، بل يُقدَّر في الفعل ويعود على الفاعل."
    },
    {
      "id": "s040",
      "type": "paragraph",
      "text": "وينقسم الضمير المستتر إلى نوعين: مستتر وجوبًا، ومستتر جوازًا."
    },
    {
      "id": "s041",
      "type": "heading",
      "text": "1- الضمير المستتر وجوبًا"
    },
    {
      "id": "s042",
      "type": "highlight",
      "label": "قاعدة",
      "text": "الضمير المستتر وجوبًا هو الذي لا يصحُّ أن يحلَّ محلَّه اسمٌ ظاهرٌ ولا ضميرٌ منفصلٌ. ويكون في أربعة مواضع: مع الفعل المضارع المبدوء بهمزة المتكلم (أنا)، أو نون المتكلم (نحن)، أو تاء المخاطب المفرد (أنتَ)، ومع فعل الأمر للمخاطب المفرد."
    },
    {
      "id": "s043",
      "type": "example",
      "style": "sentences",
      "items": [
        {
          "text": "– أَكْتُبُ الدرسَ . (التقدير: أنا)",
          "underlined": [
            "أَكْتُبُ"
          ]
        },
        {
          "text": "– نَكْتُبُ الدرسَ . (التقدير: نحن)",
          "underlined": [
            "نَكْتُبُ"
          ]
        },
        {
          "text": "– تَكْتُبُ الدرسَ . (التقدير: أنتَ)",
          "underlined": [
            "تَكْتُبُ"
          ]
        },
        {
          "text": "– اكْتُبْ الدرسَ . (التقدير: أنتَ)",
          "underlined": [
            "اكْتُبْ"
          ]
        }
      ]
    },
    {
      "id": "s044",
      "type": "heading",
      "text": "2- الضمير المستتر جوازًا"
    },
    {
      "id": "s045",
      "type": "highlight",
      "label": "قاعدة",
      "text": "الضمير المستتر جوازًا هو الذي يصحُّ أن يحلَّ محلَّه اسمٌ ظاهرٌ. ويكون مع الفعل الماضي للغائب المفرد، والفعل المضارع المبدوء بياء الغيبة أو تاء الغيبة للمؤنث المفرد."
    },
    {
      "id": "s046",
      "type": "example",
      "style": "sentences",
      "items": [
        {
          "text": "– محمدٌ كَتَبَ الدرسَ . (التقدير: هو، ويصح: كَتَبَ محمدٌ)",
          "underlined": [
            "كَتَبَ"
          ]
        },
        {
          "text": "– الطالبُ يَكْتُبُ الدرسَ . (التقدير: هو)",
          "underlined": [
            "يَكْتُبُ"
          ]
        },
        {
          "text": "– فاطمةُ تَكْتُبُ الدرسَ . (التقدير: هي)",
          "underlined": [
            "تَكْتُبُ"
          ]
        }
      ]
    },
    {
      "id": "s047",
      "type": "heading",
      "text": "ضمير الشأن وضمير الفصل"
    },
    {
      "id": "s048",
      "type": "heading",
      "text": "1- ضمير الشأن"
    },
    {
      "id": "s049",
      "type": "highlight",
      "label": "تعريف",
      "text": "ضمير الشأن: ضمير غائب يتقدَّم على جملة تفسِّره، ويُسمَّى ضمير القصة إذا كان مؤنثًا، وضمير الشأن إذا كان مذكرًا. ويُستعمل لتفخيم الكلام وتعظيمه."
    },
    {
      "id": "s050",
      "type": "example",
      "style": "sentences",
      "items": [
        {
          "text": "– هو اللهُ أحدٌ .",
          "underlined": [
            "هو"
          ]
        },
        {
          "text": "– إنَّهُ الحقُّ منتصرٌ .",
          "underlined": [
            "ه"
          ]
        }
      ]
    },
    {
      "id": "s051",
      "type": "question",
      "text": "ولكن ما فائدة استعمال ضمير الشأن ؟"
    },
    {
      "id": "s052",
      "type": "paragraph",
      "text": "فائدته تفخيم الأمر وتعظيمه، وتنبيه السامع إلى أن ما سيُذكر بعده له شأنٌ عظيم وأهمية كبيرة، كأنَّه يقول: الأمر العظيم هو كذا وكذا."
    },
    {
      "id": "s053",
      "type": "heading",
      "text": "2- ضمير الفصل"
    },
    {
      "id": "s054",
      "type": "highlight",
      "label": "تعريف",
      "text": "ضمير الفصل: ضمير رفع منفصل يقع بين المبتدأ والخبر، أو بين اسم كان (وأخواتها) وخبرها، أو بين اسم إنَّ (وأخواتها) وخبرها، ليفصل بين الخبر والصفة، ولا محلَّ له من الإعراب."
    },
    {
      "id": "s055",
      "type": "example",
      "style": "sentences",
      "items": [
        {
          "text": "– محمدٌ هو المجتهدُ .",
          "underlined": [
            "هو"
          ]
        },
        {
          "text": "– كان زيدٌ هو الفائزَ .",
          "underlined": [
            "هو"
          ]
        },
        {
          "text": "– إنَّ الكسولَ هو الخاسرُ .",
          "underlined": [
            "هو"
          ]
        }
      ]
    },
    {
      "id": "s056",
      "type": "highlight",
      "label": "ملاحظة",
      "text": "يُسمَّى (ضمير فصل) لأنه يفصل بين ما قبله وما بعده، ويفيد التوكيد والحصر والتخصيص. وهو لا يقع إلا بين معرفتين أو ما يشبه المعرفة."
    },
    {
      "id": "s057",
      "type": "heading",
      "text": "إعراب الضمائر"
    },
    {
      "id": "s058",
      "type": "highlight",
      "label": "قاعدة",
      "text": "جميع الضمائر مبنيَّةٌ، أي لا تتغيَّر صورتها بتغيُّر العوامل الداخلة عليها، ولكنها تكون في محلِّ رفعٍ، أو نصبٍ، أو جرٍّ بحسب موقعها في الجملة."
    },
    {
      "id": "s059",
      "type": "table",
      "headers": [
        "الضمير",
        "حركة البناء",
        "محل الإعراب"
      ],
      "rows": [
        [
          "أنا",
          "السكون",
          "بحسب موقعه"
        ],
        [
          "نحنُ",
          "الضم",
          "بحسب موقعه"
        ],
        [
          "أنتَ",
          "الفتح",
          "بحسب موقعه"
        ],
        [
          "أنتِ",
          "الكسر",
          "بحسب موقعه"
        ],
        [
          "هو",
          "الفتح",
          "بحسب موقعه"
        ],
        [
          "هي",
          "السكون",
          "بحسب موقعه"
        ],
        [
          "التاء المتحركة",
          "بحسب حركتها",
          "في محل رفع"
        ],
        [
          "نا الفاعلين",
          "السكون",
          "بحسب موقعها"
        ],
        [
          "ألف الاثنين",
          "السكون",
          "في محل رفع"
        ],
        [
          "واو الجماعة",
          "السكون",
          "في محل رفع"
        ],
        [
          "ياء المخاطبة",
          "السكون",
          "في محل رفع"
        ],
        [
          "نون النسوة",
          "الفتح",
          "في محل رفع"
        ]
      ]
    },
    {
      "id": "s060",
      "type": "heading",
      "text": "أمثلة معربة"
    },
    {
      "id": "s061",
      "type": "example",
      "style": "sentences",
      "items": [
        {
          "text": "– كَتَبْتُ الواجبَ .",
          "underlined": [
            "كَتَبْتُ"
          ]
        }
      ]
    },
    {
      "id": "s062",
      "type": "paragraph",
      "text": "كَتَبَ: فعل ماضٍ مبني على السكون لاتصاله بضمير رفع متحرك. التاء: ضمير متصل مبني على الضم في محل رفع فاعل. الواجبَ: مفعول به منصوب وعلامة نصبه الفتحة الظاهرة."
    },
    {
      "id": "s063",
      "type": "example",
      "style": "sentences",
      "items": [
        {
          "text": "– إيَّاكَ نعبدُ .",
          "underlined": [
            "إيَّاكَ"
          ]
        }
      ]
    },
    {
      "id": "s064",
      "type": "paragraph",
      "text": "إيَّا: ضمير منفصل مبني على السكون في محل نصب مفعول به مقدَّم. الكاف: حرف خطاب لا محلَّ له من الإعراب. نعبدُ: فعل مضارع مرفوع وعلامة رفعه الضمة الظاهرة، والفاعل ضمير مستتر وجوبًا تقديره (نحن)."
    },
    {
      "id": "s065",
      "type": "highlight",
      "label": "تنبيه",
      "text": "ينبغي على الطالب أن يميِّز بين الضمائر البارزة والمستترة، وأن يُحدِّد محلَّ كلِّ ضمير من الإعراب، فالضمائر مبنيَّةٌ دائمًا، ولا تتأثر صورتها بالعوامل، ولكن محلَّها الإعرابي يتغيَّر بحسب موقعها في الجملة."
    },
    {
      "id": "s066",
      "type": "quote",
      "text": "قال تعالى: ﴿إِيَّاكَ نَعْبُدُ وَإِيَّاكَ نَسْتَعِينُ﴾"
    },
    {
      "id": "s067",
      "type": "paragraph",
      "text": "ففي هذه الآية الكريمة (إيَّاكَ) ضمير نصب منفصل مبنيٌّ على الفتح في محلِّ نصب مفعول به مقدَّم، وقُدِّم لإفادة الحصر، أي: نعبدك وحدك ولا نعبد غيرك، ونستعين بك وحدك ولا نستعين بسواك."
    }
  ]
}
